<?xml version="1.0" encoding="UTF-8" standalone="yes"?>
<List>
    <Order id="0">
        <address>Address</address>
        <client>
            <id>0</id>
            <FirstName>Tadas</FirstName>
            <Lastname>T</Lastname>
            <Phone_Number>123</Phone_Number>
        </client>
        <driver>
            <id>0</id>
            <FirstName>Tadas</FirstName>
            <Lastname>T</Lastname>
            <Phone_Number>123</Phone_Number>
            <License_Plate>STD:123</License_Plate>
        </driver>
        <dispatch>
            <id>0</id>
            <FirstName>Tadas</FirstName>
            <Lastname>T</Lastname>
            <Phone_Number>123</Phone_Number>
            <Work_Number>+123</Work_Number>
        </dispatch>
    </Order>
</List>
