<?xml version="1.0" encoding="UTF-8" standalone="yes"?>
<List>
    <Order id="1">
        <adresas>Tuskulenu g 2</adresas>
        <klientas>
            <id>3</id>
            <FirstName>Lukas</FirstName>
            <Lastname>Kazlauskas</Lastname>
            <Phone_Number>+37087654320</Phone_Number>
        </klientas>
        <vairuotojas>
            <id>4</id>
            <FirstName>Dovydas</FirstName>
            <Lastname>Kazlauskas</Lastname>
            <Phone_Number>+37012345678</Phone_Number>
            <Car_Model>T1052</Car_Model>
        </vairuotojas>
        <despecerine>
            <id>2</id>
            <FirstName>Dovydas</FirstName>
            <Lastname>Vasiliauskas</Lastname>
            <Phone_Number>+37087654321</Phone_Number>
            <Work_Phone_Number>+37098765433</Work_Phone_Number>
        </despecerine>
    </Order>
    <Order id="5">
        <adresas>Mindaugo g 41</adresas>
        <klientas>
            <id>7</id>
            <FirstName>Andrius</FirstName>
            <Lastname>Petrauskas</Lastname>
            <Phone_Number>+37087654321</Phone_Number>
        </klientas>
        <vairuotojas>
            <id>8</id>
            <FirstName>Dovydas</FirstName>
            <Lastname>Burokas</Lastname>
            <Phone_Number>+37087654322</Phone_Number>
            <Car_Model>T4362</Car_Model>
        </vairuotojas>
        <despecerine>
            <id>6</id>
            <FirstName>Lukas</FirstName>
            <Lastname>Kazlauskas</Lastname>
            <Phone_Number>+37012345679</Phone_Number>
            <Work_Phone_Number>+37012345680</Work_Phone_Number>
        </despecerine>
    </Order>
    <Order id="9">
        <adresas>Ozo g 53</adresas>
        <klientas>
            <id>11</id>
            <FirstName>Marius</FirstName>
            <Lastname>Vasiliauskas</Lastname>
            <Phone_Number>+37087654321</Phone_Number>
        </klientas>
        <vairuotojas>
            <id>12</id>
            <FirstName>Lukas</FirstName>
            <Lastname>Kazlauskas</Lastname>
            <Phone_Number>+37098765432</Phone_Number>
            <Car_Model>T1725</Car_Model>
        </vairuotojas>
        <despecerine>
            <id>10</id>
            <FirstName>Jonas</FirstName>
            <Lastname>Zuvoskis</Lastname>
            <Phone_Number>+37012345679</Phone_Number>
            <Work_Phone_Number>+37012345678</Work_Phone_Number>
        </despecerine>
    </Order>
    <Order id="13">
        <adresas>Mindaugo g 41</adresas>
        <klientas>
            <id>15</id>
            <FirstName>Marius</FirstName>
            <Lastname>Petrauskas</Lastname>
            <Phone_Number>+37012345678</Phone_Number>
        </klientas>
        <vairuotojas>
            <id>16</id>
            <FirstName>Dovydas</FirstName>
            <Lastname>Lapinaitis</Lastname>
            <Phone_Number>+37098765431</Phone_Number>
            <Car_Model>T2052</Car_Model>
        </vairuotojas>
        <despecerine>
            <id>14</id>
            <FirstName>Andrius</FirstName>
            <Lastname>Vasiliauskas</Lastname>
            <Phone_Number>+37087654322</Phone_Number>
            <Work_Phone_Number>+37087654321</Work_Phone_Number>
        </despecerine>
    </Order>
    <Order id="17">
        <adresas>Liubarto g 30</adresas>
        <klientas>
            <id>19</id>
            <FirstName>Dovydas</FirstName>
            <Lastname>Zuvoskis</Lastname>
            <Phone_Number>+37012345679</Phone_Number>
        </klientas>
        <vairuotojas>
            <id>20</id>
            <FirstName>Matas</FirstName>
            <Lastname>Kavaliauskas</Lastname>
            <Phone_Number>+37098765432</Phone_Number>
            <Car_Model>T4362</Car_Model>
        </vairuotojas>
        <despecerine>
            <id>18</id>
            <FirstName>Tomas</FirstName>
            <Lastname>Zuvoskis</Lastname>
            <Phone_Number>+37012345680</Phone_Number>
            <Work_Phone_Number>+37098765432</Work_Phone_Number>
        </despecerine>
    </Order>
    <Order id="21">
        <adresas>Mindaugo g 41</adresas>
        <klientas>
            <id>23</id>
            <FirstName>Marius</FirstName>
            <Lastname>Jonaitis</Lastname>
            <Phone_Number>+37012345679</Phone_Number>
        </klientas>
        <vairuotojas>
            <id>24</id>
            <FirstName>Andrius</FirstName>
            <Lastname>Jonaitis</Lastname>
            <Phone_Number>+37098765431</Phone_Number>
            <Car_Model>T4362</Car_Model>
        </vairuotojas>
        <despecerine>
            <id>22</id>
            <FirstName>Domantas</FirstName>
            <Lastname>Simkus</Lastname>
            <Phone_Number>+37098765432</Phone_Number>
            <Work_Phone_Number>+37098765431</Work_Phone_Number>
        </despecerine>
    </Order>
    <Order id="25">
        <adresas>Erfurto 90</adresas>
        <klientas>
            <id>27</id>
            <FirstName>Marius</FirstName>
            <Lastname>Jonaitis</Lastname>
            <Phone_Number>+37098765431</Phone_Number>
        </klientas>
        <vairuotojas>
            <id>28</id>
            <FirstName>Andrius</FirstName>
            <Lastname>Burokas</Lastname>
            <Phone_Number>+37012345680</Phone_Number>
            <Car_Model>T5421</Car_Model>
        </vairuotojas>
        <despecerine>
            <id>26</id>
            <FirstName>Dovydas</FirstName>
            <Lastname>Jonaitis</Lastname>
            <Phone_Number>+37087654322</Phone_Number>
            <Work_Phone_Number>+37098765433</Work_Phone_Number>
        </despecerine>
    </Order>
    <Order id="29">
        <adresas>A.Kojalaviciaus 23</adresas>
        <klientas>
            <id>31</id>
            <FirstName>Andrius</FirstName>
            <Lastname>Vasiliauskas</Lastname>
            <Phone_Number>+37012345679</Phone_Number>
        </klientas>
        <vairuotojas>
            <id>32</id>
            <FirstName>Matas</FirstName>
            <Lastname>Petrauskas</Lastname>
            <Phone_Number>+37087654321</Phone_Number>
            <Car_Model>T1725</Car_Model>
        </vairuotojas>
        <despecerine>
            <id>30</id>
            <FirstName>Marius</FirstName>
            <Lastname>Jonaitis</Lastname>
            <Phone_Number>+37087654321</Phone_Number>
            <Work_Phone_Number>+37012345679</Work_Phone_Number>
        </despecerine>
    </Order>
    <Order id="33">
        <adresas>T.Narburto g 42</adresas>
        <klientas>
            <id>35</id>
            <FirstName>Matas</FirstName>
            <Lastname>Petrauskas</Lastname>
            <Phone_Number>+37012345678</Phone_Number>
        </klientas>
        <vairuotojas>
            <id>36</id>
            <FirstName>Jonas</FirstName>
            <Lastname>Jonaitis</Lastname>
            <Phone_Number>+37098765433</Phone_Number>
            <Car_Model>T5421</Car_Model>
        </vairuotojas>
        <despecerine>
            <id>34</id>
            <FirstName>Vytautas</FirstName>
            <Lastname>Jonaitis</Lastname>
            <Phone_Number>+37098765432</Phone_Number>
            <Work_Phone_Number>+37087654320</Work_Phone_Number>
        </despecerine>
    </Order>
    <Order id="37">
        <adresas>Liubarto g 30</adresas>
        <klientas>
            <id>39</id>
            <FirstName>Jonas</FirstName>
            <Lastname>Simkus</Lastname>
            <Phone_Number>+37012345680</Phone_Number>
        </klientas>
        <vairuotojas>
            <id>40</id>
            <FirstName>Andrius</FirstName>
            <Lastname>Jonaitis</Lastname>
            <Phone_Number>+37087654320</Phone_Number>
            <Car_Model>T1725</Car_Model>
        </vairuotojas>
        <despecerine>
            <id>38</id>
            <FirstName>Marius</FirstName>
            <Lastname>Burokas</Lastname>
            <Phone_Number>+37087654322</Phone_Number>
            <Work_Phone_Number>+37012345679</Work_Phone_Number>
        </despecerine>
    </Order>
</List>
